excon/__init__.py
excon/convert.py
excon/core.py
excon/datin.py
excon/helpers.py
tests/__init__.py
tests/context.py
tests/test_advanced.py
tests/test_basic.py
tests/test_convert_pdf.py
tests/test_pdf2csv_inputs.py
excon-0.1.6.dist-info/LICENSE
excon-0.1.6.dist-info/METADATA
excon-0.1.6.dist-info/WHEEL
excon-0.1.6.dist-info/top_level.txt
excon-0.1.6.dist-info/RECORD
