Metadata-Version: 2.1
Name: excon
Version: 0.1.6
Summary: Extract and convert data from PDFs
Home-page: https://github.com/rbutus/excon.git
Author: Ryan Trigg
Author-email: rbutustree@gmail.com
License: MIT License
Platform: UNKNOWN
Classifier: Programming Language :: Python :: 3
Classifier: License :: OSI Approved :: MIT License
Classifier: Operating System :: OS Independent
Requires-Dist: pandas
Requires-Dist: numpy
Requires-Dist: Wand
Requires-Dist: subprocess.run
Requires-Dist: PyPDF2
Requires-Dist: tabula-py
